pydeepimagej/DeepImageJConfig.py
pydeepimagej/__init__.py
pydeepimagej/xml/__init__.py
pydeepimagej/xml/create_config.py
pydeepimagej/yaml/__init__.py
pydeepimagej/yaml/bioimageio_specifications.py
pydeepimagej/yaml/create_config.py
pydeepimagej-2.4.dist-info/LICENSE
pydeepimagej-2.4.dist-info/METADATA
pydeepimagej-2.4.dist-info/WHEEL
pydeepimagej-2.4.dist-info/top_level.txt
pydeepimagej-2.4.dist-info/RECORD
