Metadata-Version: 2.1
Name: pydeepimagej
Version: 2.4
Summary: Python package to export TensorFlow models as DeepImageJ bundled models
Home-page: https://deepimagej.github.io/deepimagej/
Download-URL: https://github.com/deepimagej/pydeepimagej/archive/v1.0.0.tar.gz
Author: E. Gomez-de-Mariscal, C. Garcia-Lopez-de-Haro, W. Ouyang, L. Donati, E- Lundberg, M. Unser, A. Munoz-Barrutia, D. Sage.
Author-email: esgomezm@pa.uc3m.com, daniel.sage@epfl.ch, mamunozb@ing.uc3m.es
License: BSD 2-Clause License
Keywords: Fiji,ImageJ,deepImageJ,Deep Learning,Image processing,bioimage.io,BioImage Model Zoo
Classifier: Development Status :: 3 - Alpha
Classifier: Intended Audience :: Science/Research
Classifier: Intended Audience :: Education
Classifier: Topic :: Scientific/Engineering
Classifier: License :: OSI Approved :: BSD License
Classifier: Programming Language :: Python :: 3
Requires-Python: >=3.0
License-File: LICENSE
Requires-Dist: numpy
Requires-Dist: scikit-image (==0.17.2)
Requires-Dist: ruamel.yaml
Requires-Dist: datetime
